{
  "name": "Cooperative",
  "fields": [
    {
      "fieldName": "name",
      "fieldType": "String",
      "fieldValidateRules": [
        "required"
      ]
    },
    {
      "fieldName": "members",
      "fieldType": "String"
    }
  ],
  "relationships": [
    {
      "relationshipType": "one-to-many",
      "otherEntityName": "restaurant",
      "otherEntityRelationshipName": "cooperative",
      "relationshipName": "restaurant"
    }
  ],
  "changelogDate": "20210411073920",
  "entityTableName": "cooperative",
  "dto": "no",
  "pagination": "no",
  "service": "no",
  "jpaMetamodelFiltering": false,
  "fluentMethods": true,
  "readOnly": false,
  "embedded": false,
  "clientRootFolder": "",
  "applications": "*"
}
